imagewand/__init__.py
imagewand/align.py
imagewand/autocrop.py
imagewand/automerge.py
imagewand/cli.py
imagewand/config.py
imagewand/filters.py
imagewand/imageinfo.py
imagewand/pdf2img.py
imagewand/resize.py
imagewand/plugins/__init__.py
imagewand/plugins/custom_filters.py
imagewand/scripts/merge_command.py
imagewand-0.1.1.dist-info/licenses/LICENSE
imagewand-0.1.1.dist-info/METADATA
imagewand-0.1.1.dist-info/WHEEL
imagewand-0.1.1.dist-info/entry_points.txt
imagewand-0.1.1.dist-info/top_level.txt
imagewand-0.1.1.dist-info/RECORD
