Metadata-Version: 2.4
Name: imagewand
Version: 0.1.1
Summary: A Python package for image resizing and PDF to image conversion
Author-email: Tengfei Yin <tengfei@twinko.ai>
License: Apache-2.0
Project-URL: Homepage, https://github.com/twinko-ai/imagewand
Project-URL: Repository, https://github.com/twinko-ai/imagewand
Project-URL: Documentation, https://github.com/twinko-ai/imagewand#readme
Classifier: Development Status :: 4 - Beta
Classifier: Environment :: Console
Classifier: Intended Audience :: End Users/Desktop
Classifier: Operating System :: OS Independent
Classifier: Programming Language :: Python :: 3
Classifier: Programming Language :: Python :: 3.8
Classifier: Programming Language :: Python :: 3.9
Classifier: Programming Language :: Python :: 3.10
Classifier: Programming Language :: Python :: 3.11
Classifier: Topic :: Multimedia :: Graphics
Classifier: Topic :: Utilities
Classifier: License :: OSI Approved :: Apache Software License
Requires-Python: >=3.8
License-File: LICENSE
Requires-Dist: Pillow
Requires-Dist: pdf2image
Requires-Dist: requests>=2.31.0
Requires-Dist: tqdm
Requires-Dist: PyMuPDF
Requires-Dist: opencv-python
Requires-Dist: numpy
Requires-Dist: click
Requires-Dist: black>=24.8.0
Requires-Dist: isort>=5.12.0
Dynamic: license-file
